botframework/__init__.py
botframework/commandSystem.py
botframework/defaultCommands.py
botframework/eventSystem.py
botframework/exception.py
botframework/fileSystem.py
botframework/flags.py
botframework/logging.py
botframework/moduleUtils.py
botframework/server.py
botframework/types.py
botframework/utils.py
botframework/abc/__init__.py
botframework/abc/eventSystem.py
botframework/abc/fileSystem.py
botframework/abc/server.py
botframework/abc/database/__init__.py
botframework/abc/database/backend.py
botframework/abc/database/database.py
botframework/abc/database/guild.py
botframework/database/__init__.py
botframework/database/backend.py
botframework/database/database.py
botframework/database/guild.py
botframework/dataclass/__init__.py
botframework/dataclass/user.py
botframework_enderzombi102-1.0.0.dev1.dist-info/LICENSE
botframework_enderzombi102-1.0.0.dev1.dist-info/METADATA
botframework_enderzombi102-1.0.0.dev1.dist-info/WHEEL
botframework_enderzombi102-1.0.0.dev1.dist-info/top_level.txt
botframework_enderzombi102-1.0.0.dev1.dist-info/RECORD
